[
  {
    "nombreDificultad": "Super Easy",
    "preguntas": [
      {
        "enunciado": "¿Cuál es la flor nacional de Japón?",
        "respuestas": [
          { "texto": "Flor de Loto" },
          { "texto": "Flor Pálida" },
          { "texto": "Flor de Cerezo" },
          { "texto": "Flor Tulipán" }
        ],
        "respuestaCorrecta": 2
        
      },
      {
        "enunciado": "¿Qué país tiene la mayor cantidad de islas en el mundo?",
        "respuestas": [
          { "texto": "Estados Unidos" },
          { "texto": "Suecia" },
          { "texto": "China" },
          { "texto": "Brasil" }
        ],
        "respuestaCorrecta": 1
      },
      {
        "enunciado": "¿Cuál es el idioma que tiene más palabras (según su diccionario)?",
        "respuestas": [
          { "texto": "Español" },
          { "texto": "Inglés" },
          { "texto": "Koreano" },
          { "texto": "Francés" }
        ],
        "respuestaCorrecta": 1
      },
      {
        "enunciado": "¿Cuál fue el primer largometraje de Pixar?",
        "respuestas": [
          { "texto": "Moana" },
          { "texto": "Toy Story" },
          { "texto": "Tarzán" },
          { "texto": "Pinocho" }
        ],
        "respuestaCorrecta": 1
      },
      {
        "enunciado": "¿Cómo se llama la icónica cafetería de Friends?",
        "respuestas": [
          { "texto": "Coffee Babe" },
          { "texto": "Central Park" },
          { "texto": "Coffee Break" },
          { "texto": "Central Perk" }
        ],
        "respuestaCorrecta": 3
      }
    ]
  },
  {
    "nombreDificultad": "Easy",
    "preguntas": [
      {
        "enunciado": "¿En qué año se fundó Netflix:?",
        "respuestas": [
          { "texto": "1997" },
          { "texto": "2001" },
          { "texto": "2009" },
          { "texto": "2015" }
        ],
        "respuestaCorrecta": 0
      },
      {
        "enunciado": "¿Cuál fue la serie más vista en Netflix en el 2019?",
        "respuestas": [
          { "texto": "Modern Family" },
          { "texto": "Stranger Things" },
          { "texto": "How I Met Your Mother" },
          { "texto": "Friends" }
        ],
        "respuestaCorrecta": 1
      },
      {
        "enunciado": "¿Cuál fue la primer película de Disney?",
        "respuestas": [
          { "texto": "Blanca Nieves" },
          { "texto": "Toy Story" },
          { "texto": "Bella y la Bestia" },
          { "texto": "Bambi" }
        ],
        "respuestaCorrecta": 0
      },
      {
        "enunciado": "¿Quién es el autor de la frase -Pienso, luego existo-?",
        "respuestas": [
          { "texto": "Platón" },
          { "texto": "Sócrates" },
          { "texto": "Descartes" },
          { "texto": "Francis Bacon" }
        ],
        "respuestaCorrecta": 2
      }
      
    ]
  },
  {
    "nombreDificultad": "Medium",
    "preguntas": [
      {
        "enunciado": "¿De qué ciudad son originarios los Beatles?",
        "respuestas": [
          { "texto": "Londres" },
          { "texto": "Mánchester" },
          { "texto": "Oxford" },
          { "texto": "Liverpool" }
        ],
        "respuestaCorrecta": 3
      },
      {
        "enunciado": "¿Cuántas teclas tiene un piano?",
        "respuestas": [
          { "texto": "80" },
          { "texto": "88" },
          { "texto": "90" },
          { "texto": "98" }
        ],
        "respuestaCorrecta": 1
      },
      {
        "enunciado": "¿Cuántos litros de sangre tiene una persona adulta?",
        "respuestas": [
          { "texto": "Entre 2 y 4L" },
          { "texto": "Entre 4 y 6L" },
          { "texto": "10L" },
          { "texto": "0,5L" }
        ],
        "respuestaCorrecta": 1
      },
      {
        "enunciado": "¿Cuál es el libro más vendido en el mundo después de la Biblia?",
        "respuestas": [
          { "texto": "El Señor de los Anillos" },
          { "texto": "Don Quijote de la Mancha" },
          { "texto": "Cien años de Soledad" },
          { "texto": "La Odisea" }
        ],
        "respuestaCorrecta": 1
      },
      {
        "enunciado": "La sal común está formada por dos elementos, ¿cuáles son?",
        "respuestas": [
          { "texto": "Sodio y potasio" },
          { "texto": "Sodio y cloro" },
          { "texto": "Sodio y carbono" },
          { "texto": "Potasio y cloro" }
        ],
        "respuestaCorrecta": 1
      }
    ]
  },
  {
    "nombreDificultad": "Hard",
    "preguntas": [
      {
        "enunciado": "¿Cuántos jugadores por equipo participan en un partido de voleibol?",
        "respuestas": [
          { "texto": "2" },
          { "texto": "4" },
          { "texto": "6" },
          { "texto": "12" }
        ],
        "respuestaCorrecta": 2
      },
      {
        "enunciado": "¿Cuál es el país más grande y el más pequeño del mundo?",
        "respuestas": [
          { "texto": "Canadá y Mónaco" },
          { "texto": "China y Nauru" },
          { "texto": "Estados Unidos y Malta" },
          { "texto": "Rusia y Vaticano" }
        ],
        "respuestaCorrecta": 3
      },
      {
        "enunciado": "¿Quién pintó la obra -Guernica-?",
        "respuestas": [
          { "texto": "Pablo Picasso" },
          { "texto": "Diego Rivera" },
          { "texto": "Salvador Dalí" },
          { "texto": "Frida Kahlo" }
        ],
        "respuestaCorrecta": 0
      },
      {
        "enunciado": "¿Cuánto tiempo tarda la luz del Sol en llegar a la Tierra?",
        "respuestas": [
          { "texto": "12 minutos" },
          { "texto": "1 día" },
          { "texto": "12 horas" },
          { "texto": "8 minutos" }
        ],
        "respuestaCorrecta": 3
      },
      {
        "enunciado": "Cuál es la altura de la red de voleibol en los juegos masculino y femenino?",
        "respuestas": [
          { "texto": "1,8 m y 1,5 m" },
          { "texto": "2,43 m y 2,24 m" },
          { "texto": "2,45 m y 2,15 m" },
          { "texto": "2,5 m y 2,0 m" }
        ],
        "respuestaCorrecta": 1
      }
    ]
  },
  {
    "nombreDificultad": "Extra Hard",
    "preguntas": [
      {
        "enunciado": "¿En qué periodo de la prehistoria fue descubierto el fuego?",
        "respuestas": [
          { "texto": "Neolítico" },
          { "texto": "Paleolítico" },
          { "texto": "Edad media" },
          { "texto": "Edad de piedra" }
        ],
        "respuestaCorrecta": 1
      },
      {
        "enunciado": "¿Cuál es la montaña más alta del continente americano?",
        "respuestas": [
          { "texto": "Monte Everest" },
          { "texto": "Pico Neblina" },
          { "texto": "Aconcagua" },
          { "texto": "Monte Fuji" }
        ],
        "respuestaCorrecta": 2
      },
      {
        "enunciado": "¿Cuál es la velocidad de la luz?",
        "respuestas": [
          { "texto": "150 000 000 metros por segundo" },
          { "texto": "199 792 458 metros por segundo" },
          { "texto": "300 000 000 metros por segundo" },
          { "texto": "299 792 458 metros por segundo" }
        ],
        "respuestaCorrecta": 3
      },
      {
        "enunciado": " ¿En qué país de África el español es la lengua oficial?",
        "respuestas": [
          { "texto": "Guinea ecuatorial" },
          { "texto": "Costa de Marfil" },
          { "texto": "Cabo Verde" },
          { "texto": "Liberia" }
        ],
        "respuestaCorrecta": 0
      },
      {
        "enunciado": "¿Cuál de estos países se extiende entre dos continentes?",
        "respuestas": [
          { "texto": "Tanzania" },
          { "texto": "Rusia" },
          { "texto": "Egipto" },
          { "texto": "Filipinas" }
        ],
        "respuestaCorrecta": 1
      }
    ]
  }
]
